{
  "categorias": [
    {
      "id": 1,
      "titulo": "Bleach",
      "cor": "#ff6a00",
      "link_extra": {
        "text": "Bleach - Todas as Opening",
        "url": "https://www.youtube.com/watch?v=b9vIpu0kAbE&t=4s"
      }   
    }
  ],
  "videos": [
    {
      "id": 50,
      "categoriaId": 6,
      "titulo": "Bleach",
      "description": "Yamamoto vs Wonderweiss (Legendado PT-BR)",
      "url": "https://www.youtube.com/watch?v=AzjlaXzsXfc&t=28s"
    },
    {
      "id": 51,
      "categoriaId": 6,
      "titulo": "Kenpachi Zaraki vs. Nnoitra",
      "description": "Kenpachi Zaraki vs. Nnoitra",
      "url": "https://www.youtube.com/watch?v=AMLcE2pefA8"
    }    
  ]
}